openbalkans/__init__.py
openbalkans/base.py
openbalkans/common.py
openbalkans/config.py
openbalkans/encryption.py
openbalkans/entities.py
openbalkans/exceptions.py
openbalkans/protocol.py
openbalkans-0.1.2.dist-info/AUTHORS.rst
openbalkans-0.1.2.dist-info/LICENSE
openbalkans-0.1.2.dist-info/METADATA
openbalkans-0.1.2.dist-info/WHEEL
openbalkans-0.1.2.dist-info/top_level.txt
openbalkans-0.1.2.dist-info/RECORD
