Metadata-Version: 2.1
Name: openbalkans
Version: 0.1.2
Summary: A python implementation of OpenBalkans
Home-page: https://github.com/openbalkans/openbalkans-python
Author: Barak Avrahami
Author-email: barak1345@gmail.com
License: MIT license
Keywords: openbalkans
Platform: UNKNOWN
Classifier: Development Status :: 2 - Pre-Alpha
Classifier: Intended Audience :: Developers
Classifier: License :: OSI Approved :: MIT License
Classifier: Natural Language :: English
Classifier: Programming Language :: Python :: 3
Classifier: Programming Language :: Python :: 3.4
Classifier: Programming Language :: Python :: 3.5
Classifier: Programming Language :: Python :: 3.6
Classifier: Programming Language :: Python :: 3.7
Requires-Python: >=3
Requires-Dist: cryptography (==2.8)
Requires-Dist: w3lib (==1.21.0)
